Metadata-Version: 2.1
Name: SimpleAppGui
Version: 0.5.0
Summary: Simple gui library for app development
Author: Jack Ronn
Author-email: jackronnstudios@gmail.com
